AsyncKandinsky/API_types.py
AsyncKandinsky/DefaultParams.py
AsyncKandinsky/URLS.py
AsyncKandinsky/__init__.py
AsyncKandinsky/api.py
asynckandinsky-3.0.1.dist-info/METADATA
asynckandinsky-3.0.1.dist-info/WHEEL
asynckandinsky-3.0.1.dist-info/top_level.txt
asynckandinsky-3.0.1.dist-info/RECORD
