Metadata-Version: 2.4
Name: AsyncKandinsky
Version: 3.0.1
Summary: This module is designed for asynchronous use of the kandinsky neural network and easy integration into your project.
Home-page: https://github.com/s1rne/kandinsky-async-api
Author: s1rne
Author-email: s.simaranov8@gmail.com
Project-URL: GitHub, https://github.com/s1rne/kandinsky-async-api
Keywords: kandinsky text2img async api
Classifier: Programming Language :: Python :: 3.9
Classifier: License :: OSI Approved :: MIT License
Classifier: Operating System :: OS Independent
Requires-Python: >=3.6
Requires-Dist: aiohttp>=3.8.4
Dynamic: author
Dynamic: author-email
Dynamic: classifier
Dynamic: description
Dynamic: description-content-type
Dynamic: home-page
Dynamic: keywords
Dynamic: project-url
Dynamic: requires-dist
Dynamic: requires-python
Dynamic: summary
